{"data":{"domains":172,"links":1658,"follow":1760,"nofollow":57,"text":1796,"frame":0,"form":0,"image":21,"sitewides_main":0,"sitewides_total":0,"ip":204,"ipclassc":180,"total":1817,"geodomains":{"be":2,"br":1,"ca":6,"ch":1,"cn":1,"de":12,"es":1,"fr":89,"gb":1,"ie":9,"jp":1,"kr":1,"nl":11,"pl":1,"ru":1,"us":46,"vn":2},"zones":{"be":2,"cat":1,"co":1,"com":86,"eu":1,"fr":57,"gr":1,"io":1,"net":5,"org":12},"score":20,"trust_score":26,"ascore":37,"score_prev":20,"trust_score_prev":26,"ascore_prev":37,"updated":1554840686,"backlinks":{"limit":0,"offset":0,"data":null,"caps":null,"total":0},"refdomains":{"target":"","data":null,"caps":null,"offset":0,"limit":0,"total":0},"pages":{"limit":0,"offset":0,"data":null,"caps":null,"total":0},"anchors":{"target":"","data":[{"anchor":"cr","domains_num":2,"backlinks_num":911,"first_seen":1483891796,"last_seen":1554805663,"urlanchor":false},{"anchor":"wakatoon","domains_num":102,"backlinks_num":487,"first_seen":1424199942,"last_seen":1554807931,"urlanchor":false},{"anchor":"http://fr.wakatoon.com/","domains_num":7,"backlinks_num":54,"first_seen":1493243639,"last_seen":1554805917,"urlanchor":true},{"anchor":"\u003cEmptyAnchor\u003e","domains_num":11,"backlinks_num":33,"first_seen":1531890937,"last_seen":1554758811,"urlanchor":false},{"anchor":"\u003cEmptyAnchor\u003e","domains_num":15,"backlinks_num":32,"first_seen":1549407248,"last_seen":1554560188,"urlanchor":false},{"anchor":"http://fr.wakatoon.com","domains_num":4,"backlinks_num":25,"first_seen":1504799190,"last_seen":1554751615,"urlanchor":true},{"anchor":"www.wakatoon.com","domains_num":6,"backlinks_num":23,"first_seen":1424199942,"last_seen":1554790624,"urlanchor":true},{"anchor":"http://www.wakatoon.com","domains_num":4,"backlinks_num":18,"first_seen":1505476345,"last_seen":1554528132,"urlanchor":true},{"anchor":"http://fr.wakatoon.com/boutique","domains_num":5,"backlinks_num":14,"first_seen":1516338395,"last_seen":1554545581,"urlanchor":true},{"anchor":"découvrir wakatoon","domains_num":2,"backlinks_num":14,"first_seen":1549709702,"last_seen":1554544813,"urlanchor":false},{"anchor":"https://www.wakatoon.com/download?os=ios\u0026cn=160618fb","domains_num":1,"backlinks_num":12,"first_seen":1479844709,"last_seen":1554572950,"urlanchor":true},{"anchor":"wakatoon.com","domains_num":7,"backlinks_num":12,"first_seen":1498365888,"last_seen":1554544092,"urlanchor":true},{"anchor":"https://www.wakatoon.com/download?os=android\u0026cn=160618fb","domains_num":1,"backlinks_num":12,"first_seen":1479844709,"last_seen":1554572950,"urlanchor":true},{"anchor":"tester plusieurs planches gratuitement sur leur site","domains_num":1,"backlinks_num":10,"first_seen":1553204010,"last_seen":1554650013,"urlanchor":false},{"anchor":"coloriages animés","domains_num":1,"backlinks_num":8,"first_seen":1480971935,"last_seen":1554692271,"urlanchor":false},{"anchor":"wakatoon, quand le coloriage vie","domains_num":1,"backlinks_num":7,"first_seen":1535326729,"last_seen":1552689005,"urlanchor":false},{"anchor":"\u003cEmptyAnchor\u003e","domains_num":2,"backlinks_num":6,"first_seen":1549087950,"last_seen":1554617046,"urlanchor":false},{"anchor":"cahier de dessin animé","domains_num":1,"backlinks_num":5,"first_seen":1508457783,"last_seen":1554783449,"urlanchor":false},{"anchor":"l’appli qui anime les coloriages","domains_num":1,"backlinks_num":5,"first_seen":1497364335,"last_seen":1554550707,"urlanchor":false},{"anchor":"coloriage animé","domains_num":2,"backlinks_num":4,"first_seen":1486584276,"last_seen":1554158996,"urlanchor":false},{"anchor":"libros para colorear disponibles","domains_num":1,"backlinks_num":4,"first_seen":1534575840,"last_seen":1554346514,"urlanchor":false},{"anchor":"fr.wakatoon.com","domains_num":3,"backlinks_num":4,"first_seen":1504378033,"last_seen":1551726351,"urlanchor":true},{"anchor":"http://www.wakatoon.com/","domains_num":3,"backlinks_num":4,"first_seen":1527530467,"last_seen":1554762139,"urlanchor":true},{"anchor":"website","domains_num":1,"backlinks_num":4,"first_seen":1517950056,"last_seen":1545782815,"urlanchor":false},{"anchor":"wakatoon à télécharger","domains_num":1,"backlinks_num":4,"first_seen":1515973261,"last_seen":1554648677,"urlanchor":false},{"anchor":"offer it!","domains_num":1,"backlinks_num":4,"first_seen":1517950056,"last_seen":1545782815,"urlanchor":false},{"anchor":"wakatoon (wakatoon studio)","domains_num":1,"backlinks_num":4,"first_seen":1527739930,"last_seen":1554794933,"urlanchor":false},{"anchor":"lbc","domains_num":1,"backlinks_num":3,"first_seen":1486584276,"last_seen":1554158996,"urlanchor":false},{"anchor":"offrir wakatoon","domains_num":1,"backlinks_num":3,"first_seen":1534614274,"last_seen":1554607964,"urlanchor":false},{"anchor":"grâce à l'application wakatoon","domains_num":2,"backlinks_num":3,"first_seen":1548686553,"last_seen":1554222371,"urlanchor":false},{"anchor":"en savoir plus","domains_num":2,"backlinks_num":3,"first_seen":1548686553,"last_seen":1554222371,"urlanchor":false},{"anchor":"site wakatoon","domains_num":1,"backlinks_num":2,"first_seen":1493447067,"last_seen":1550894127,"urlanchor":false},{"anchor":"https://www.wakatoon.com/","domains_num":1,"backlinks_num":2,"first_seen":1550587926,"last_seen":1553569499,"urlanchor":true},{"anchor":"site à découvrir","domains_num":1,"backlinks_num":2,"first_seen":1553937476,"last_seen":1554431790,"urlanchor":false},{"anchor":"app store","domains_num":1,"backlinks_num":2,"first_seen":1549043717,"last_seen":1554596547,"urlanchor":false},{"anchor":"google play","domains_num":1,"backlinks_num":2,"first_seen":1549043717,"last_seen":1554596547,"urlanchor":false},{"anchor":"les bras cassés","domains_num":1,"backlinks_num":2,"first_seen":1549457799,"last_seen":1554596547,"urlanchor":false},{"anchor":"des applications pour l'école","domains_num":1,"backlinks_num":2,"first_seen":1534899693,"last_seen":1546245399,"urlanchor":false},{"anchor":"l'appli est dispo","domains_num":1,"backlinks_num":2,"first_seen":1498365888,"last_seen":1539167795,"urlanchor":false},{"anchor":"ici","domains_num":2,"backlinks_num":2,"first_seen":1541179716,"last_seen":1551214285,"urlanchor":false},{"anchor":"(cliquez ici pour suivre le lien)","domains_num":1,"backlinks_num":2,"first_seen":1492080793,"last_seen":1554069929,"urlanchor":false},{"anchor":"sur le site wakatoon","domains_num":2,"backlinks_num":2,"first_seen":1548551132,"last_seen":1554282051,"urlanchor":false},{"anchor":"créativité et originalité : les coloriages se transformant en dessin animé","domains_num":1,"backlinks_num":2,"first_seen":1499650789,"last_seen":1553939603,"urlanchor":false},{"anchor":"idée cadeau pour enfants : coloriages animés","domains_num":1,"backlinks_num":2,"first_seen":1543156324,"last_seen":1554048234,"urlanchor":false},{"anchor":"pink rose","domains_num":1,"backlinks_num":2,"first_seen":1549457799,"last_seen":1554596547,"urlanchor":false},{"anchor":"le père noël est en retard","domains_num":1,"backlinks_num":2,"first_seen":1549457799,"last_seen":1554596547,"urlanchor":false},{"anchor":"lucky luke à la poursuite des dalton","domains_num":1,"backlinks_num":1,"first_seen":1551269839,"last_seen":1554596547,"urlanchor":false},{"anchor":"misez sur l’originalité avec des albums de coloriage animé !","domains_num":1,"backlinks_num":1,"first_seen":1501447069,"last_seen":1550464605,"urlanchor":false},{"anchor":"livres de 8 coloriages","domains_num":1,"backlinks_num":1,"first_seen":1483062471,"last_seen":1550902729,"urlanchor":false},{"anchor":"idée cadeau pour enfants : albums de coloriage animé","domains_num":1,"backlinks_num":1,"first_seen":1503411748,"last_seen":1552693311,"urlanchor":false},{"anchor":"http://fr.wakatoon.com/les-bras-casses","domains_num":1,"backlinks_num":1,"first_seen":1543046585,"last_seen":1548538184,"urlanchor":true},{"anchor":"les dessins à colorier","domains_num":1,"backlinks_num":1,"first_seen":1509132871,"last_seen":1546727652,"urlanchor":false},{"anchor":"http://fr.wakatoon.com/lfodg-instructions","domains_num":1,"backlinks_num":1,"first_seen":1543046585,"last_seen":1552901055,"urlanchor":true},{"anchor":"http://fr.wakatoon.com/boutique/","domains_num":1,"backlinks_num":1,"first_seen":1546462613,"last_seen":1552923261,"urlanchor":true},{"anchor":"awa et l’oiseau aux instruments","domains_num":1,"backlinks_num":1,"first_seen":1545467690,"last_seen":1552425091,"urlanchor":false},{"anchor":"livres de coloriage animés","domains_num":1,"backlinks_num":1,"first_seen":1549457799,"last_seen":1554473326,"urlanchor":false},{"anchor":"déjà disponibles","domains_num":1,"backlinks_num":1,"first_seen":1530639281,"last_seen":1553766735,"urlanchor":false},{"anchor":"http://fr.wakatoon.com/?utm_source=partenariat\u0026utm_medium=usbek-rica\u0026utm_campaign=e-shop","domains_num":1,"backlinks_num":1,"first_seen":1542621856,"last_seen":1554187278,"urlanchor":true},{"anchor":"coloriages animés wakatoon","domains_num":1,"backlinks_num":1,"first_seen":1518696627,"last_seen":1551152544,"urlanchor":false},{"anchor":"http://fr.wakatoon.com/agences-partenaires","domains_num":1,"backlinks_num":1,"first_seen":1543046585,"last_seen":1552901055,"urlanchor":true},{"anchor":"voici le site internet","domains_num":1,"backlinks_num":1,"first_seen":1545062043,"last_seen":1553879769,"urlanchor":false},{"anchor":"http://fr.wakatoon.com/animations","domains_num":1,"backlinks_num":1,"first_seen":1548538184,"last_seen":1552901055,"urlanchor":true},{"anchor":"wakatoon (nouvelle fenêtre)","domains_num":1,"backlinks_num":1,"first_seen":1529914883,"last_seen":1554392531,"urlanchor":false},{"anchor":"http://fr.wakatoon.com/pre-commander","domains_num":1,"backlinks_num":1,"first_seen":1543046585,"last_seen":1552901055,"urlanchor":true},{"anchor":"commandez le livre de coloriage animé essi dans la forêt des monstres directement sur le site de wakatoon","domains_num":1,"backlinks_num":1,"first_seen":1549457799,"last_seen":1554473326,"urlanchor":false},{"anchor":"miraculous","domains_num":1,"backlinks_num":1,"first_seen":1551269839,"last_seen":1554596547,"urlanchor":false},{"anchor":"marsupilami - la photo parfaite","domains_num":1,"backlinks_num":1,"first_seen":1551269839,"last_seen":1554596547,"urlanchor":false},{"anchor":"pixpole","domains_num":1,"backlinks_num":1,"first_seen":1551118441,"last_seen":1552747994,"urlanchor":false},{"anchor":"boule \u0026 bill - la bonne cachette et autres histoires","domains_num":1,"backlinks_num":1,"first_seen":1551269839,"last_seen":1554596547,"urlanchor":false},{"anchor":"version pédagogique de wakatoon","domains_num":1,"backlinks_num":1,"first_seen":1551269839,"last_seen":1554596547,"urlanchor":false},{"anchor":"visiter le site","domains_num":1,"backlinks_num":1,"first_seen":1554786786,"last_seen":1554786786,"urlanchor":false},{"anchor":"site internet","domains_num":1,"backlinks_num":1,"first_seen":1550839307,"last_seen":1552585870,"urlanchor":false},{"anchor":"quand les coloriages prennent vie","domains_num":1,"backlinks_num":1,"first_seen":1504062355,"last_seen":1548565114,"urlanchor":false},{"anchor":"les livres de coloriage animé wakatoon","domains_num":1,"backlinks_num":1,"first_seen":1540788961,"last_seen":1542664124,"urlanchor":false},{"anchor":"wacatoon","domains_num":1,"backlinks_num":1,"first_seen":1545052797,"last_seen":1545052797,"urlanchor":false},{"anchor":"yakari et les mocassins magiques","domains_num":1,"backlinks_num":1,"first_seen":1551269839,"last_seen":1554596547,"urlanchor":false},{"anchor":"wakatoon propose des coloriages sur papier qui se transforment en dessin animé grâce à une application","domains_num":1,"backlinks_num":1,"first_seen":1545991217,"last_seen":1553951025,"urlanchor":false},{"anchor":"spirou et la trottinette tout-terrain","domains_num":1,"backlinks_num":1,"first_seen":1551269839,"last_seen":1554596547,"urlanchor":false},{"anchor":"awa et l'oiseau aux instruments","domains_num":1,"backlinks_num":1,"first_seen":1551269839,"last_seen":1554596547,"urlanchor":false},{"anchor":"télécharger gratuitement wakatoon sur apple store et google play.","domains_num":1,"backlinks_num":1,"first_seen":1549079616,"last_seen":1549079616,"urlanchor":false},{"anchor":"http://fr.wakatoon.com/anniversaires","domains_num":1,"backlinks_num":1,"first_seen":1543046585,"last_seen":1552901055,"urlanchor":true},{"anchor":"http://fr.wakatoon.com/accueil","domains_num":1,"backlinks_num":1,"first_seen":1543046585,"last_seen":1552901055,"urlanchor":true},{"anchor":"http://wakatoon.com","domains_num":1,"backlinks_num":1,"first_seen":1543046585,"last_seen":1552901055,"urlanchor":true},{"anchor":"http://wakatoon.com/","domains_num":1,"backlinks_num":1,"first_seen":1543046585,"last_seen":1552901055,"urlanchor":true},{"anchor":"http://wakatoon.com/code","domains_num":1,"backlinks_num":1,"first_seen":1543046585,"last_seen":1552901055,"urlanchor":true},{"anchor":"\u003cEmptyAnchor\u003e","domains_num":1,"backlinks_num":1,"first_seen":1552241229,"last_seen":1554593604,"urlanchor":false},{"anchor":"\u003cEmptyAnchor\u003e","domains_num":1,"backlinks_num":1,"first_seen":1552326234,"last_seen":1554773195,"urlanchor":false},{"anchor":"\u003cEmptyAnchor\u003e","domains_num":1,"backlinks_num":1,"first_seen":1553314204,"last_seen":1553314204,"urlanchor":false},{"anchor":"essi dans la forêt des monstres","domains_num":1,"backlinks_num":1,"first_seen":1551269839,"last_seen":1554596547,"urlanchor":false},{"anchor":"\u003cEmptyAnchor\u003e","domains_num":1,"backlinks_num":1,"first_seen":1553008507,"last_seen":1554058254,"urlanchor":false},{"anchor":"\u003cEmptyAnchor\u003e","domains_num":1,"backlinks_num":1,"first_seen":1549905650,"last_seen":1552742073,"urlanchor":false},{"anchor":"\u003cEmptyAnchor\u003e","domains_num":1,"backlinks_num":1,"first_seen":1552918912,"last_seen":1552918912,"urlanchor":false},{"anchor":"\u003cEmptyAnchor\u003e","domains_num":1,"backlinks_num":1,"first_seen":1552076799,"last_seen":1554507314,"urlanchor":false},{"anchor":"\u003cEmptyAnchor\u003e","domains_num":1,"backlinks_num":1,"first_seen":1552522050,"last_seen":1553893212,"urlanchor":false},{"anchor":"\u003cEmptyAnchor\u003e","domains_num":1,"backlinks_num":1,"first_seen":1552470788,"last_seen":1553843656,"urlanchor":false},{"anchor":"\u003cEmptyAnchor\u003e","domains_num":1,"backlinks_num":1,"first_seen":1551802038,"last_seen":1553691885,"urlanchor":false},{"anchor":"\u003cEmptyAnchor\u003e","domains_num":1,"backlinks_num":1,"first_seen":1553209909,"last_seen":1554281057,"urlanchor":false},{"anchor":"\u003cEmptyAnchor\u003e","domains_num":1,"backlinks_num":1,"first_seen":1551711615,"last_seen":1554715035,"urlanchor":false},{"anchor":"\u003cEmptyAnchor\u003e","domains_num":1,"backlinks_num":1,"first_seen":1549128947,"last_seen":1554398394,"urlanchor":false},{"anchor":"les monsieur madame reprennent des couleurs","domains_num":1,"backlinks_num":1,"first_seen":1551269839,"last_seen":1554596547,"urlanchor":false}],"caps":null,"offset":0,"limit":0,"total":101},"historical":{"domain_stat":{"months":{"1422748800":{"lostLinks":3,"newLinks":6,"totalLinks":6},"1425168000":{"lostLinks":1,"newLinks":1,"totalLinks":7},"1427846400":{"lostLinks":0,"newLinks":0,"totalLinks":7},"1430438400":{"lostLinks":0,"newLinks":0,"totalLinks":7},"1433116800":{"lostLinks":0,"newLinks":1,"totalLinks":8},"1435708800":{"lostLinks":1,"newLinks":1,"totalLinks":9},"1438387200":{"lostLinks":0,"newLinks":1,"totalLinks":10},"1441065600":{"lostLinks":0,"newLinks":2,"totalLinks":8},"1443657600":{"lostLinks":0,"newLinks":2,"totalLinks":9},"1446336000":{"lostLinks":0,"newLinks":1,"totalLinks":10},"1448928000":{"lostLinks":0,"newLinks":0,"totalLinks":10},"1451606400":{"lostLinks":0,"newLinks":0,"totalLinks":10},"1454284800":{"lostLinks":2,"newLinks":3,"totalLinks":12},"1456790400":{"lostLinks":2,"newLinks":7,"totalLinks":18},"1459468800":{"lostLinks":0,"newLinks":5,"totalLinks":23},"1462060800":{"lostLinks":0,"newLinks":0,"totalLinks":23},"1464739200":{"lostLinks":0,"newLinks":0,"totalLinks":23},"1467331200":{"lostLinks":0,"newLinks":4,"totalLinks":27},"1470009600":{"lostLinks":0,"newLinks":2,"totalLinks":28},"1472688000":{"lostLinks":0,"newLinks":0,"totalLinks":26},"1475280000":{"lostLinks":0,"newLinks":0,"totalLinks":23},"1477958400":{"lostLinks":2,"newLinks":8,"totalLinks":29},"1480550400":{"lostLinks":1,"newLinks":17,"totalLinks":46},"1483228800":{"lostLinks":3,"newLinks":51,"totalLinks":97},"1485907200":{"lostLinks":2,"newLinks":33,"totalLinks":130},"1488326400":{"lostLinks":1,"newLinks":8,"totalLinks":137},"1491004800":{"lostLinks":5,"newLinks":73,"totalLinks":210},"1493596800":{"lostLinks":4,"newLinks":33,"totalLinks":242},"1496275200":{"lostLinks":8,"newLinks":39,"totalLinks":277},"1498867200":{"lostLinks":4,"newLinks":35,"totalLinks":310},"1501545600":{"lostLinks":0,"newLinks":77,"totalLinks":374},"1504224000":{"lostLinks":1,"newLinks":48,"totalLinks":406},"1506816000":{"lostLinks":6,"newLinks":39,"totalLinks":440},"1509494400":{"lostLinks":1,"newLinks":49,"totalLinks":477},"1512086400":{"lostLinks":26,"newLinks":73,"totalLinks":498},"1514764800":{"lostLinks":25,"newLinks":93,"totalLinks":578},"1517443200":{"lostLinks":6,"newLinks":56,"totalLinks":620},"1519862400":{"lostLinks":4,"newLinks":49,"totalLinks":658},"1522540800":{"lostLinks":11,"newLinks":49,"totalLinks":685},"1525132800":{"lostLinks":20,"newLinks":38,"totalLinks":701},"1527811200":{"lostLinks":25,"newLinks":63,"totalLinks":747},"1530403200":{"lostLinks":21,"newLinks":62,"totalLinks":772},"1533081600":{"lostLinks":9,"newLinks":58,"totalLinks":796},"1535760000":{"lostLinks":21,"newLinks":84,"totalLinks":863},"1538352000":{"lostLinks":58,"newLinks":168,"totalLinks":1002},"1541030400":{"lostLinks":51,"newLinks":158,"totalLinks":1130},"1543622400":{"lostLinks":40,"newLinks":205,"totalLinks":1310},"1546300800":{"lostLinks":16,"newLinks":135,"totalLinks":1409},"1548979200":{"lostLinks":28,"newLinks":276,"totalLinks":1657},"1551398400":{"lostLinks":50,"newLinks":141,"totalLinks":1776},"1554076800":{"lostLinks":0,"newLinks":84,"totalLinks":1843}},"weeks":{"1548028800":{"lostLinks":6,"newLinks":34,"totalLinks":1381},"1548633600":{"lostLinks":2,"newLinks":46,"totalLinks":1417},"1549238400":{"lostLinks":4,"newLinks":81,"totalLinks":1484},"1549843200":{"lostLinks":5,"newLinks":45,"totalLinks":1526},"1550448000":{"lostLinks":11,"newLinks":59,"totalLinks":1581},"1551052800":{"lostLinks":8,"newLinks":84,"totalLinks":1659},"1551657600":{"lostLinks":15,"newLinks":38,"totalLinks":1696},"1552262400":{"lostLinks":13,"newLinks":38,"totalLinks":1732},"1552867200":{"lostLinks":22,"newLinks":20,"totalLinks":1750},"1553472000":{"lostLinks":0,"newLinks":22,"totalLinks":1769},"1554076800":{"lostLinks":0,"newLinks":77,"totalLinks":1836},"1554681600":{"lostLinks":0,"newLinks":7,"totalLinks":1823}}}},"topics":{},"topics_profile":{}},"caps":{"fly":true,"topics_profile":true},"status":"SUCCESS","exec_time":0.009722442,"thirdparty_time":0,"base_time":0}